LICENSE
README.md
setup.cfg
setup.py
cz_sqlglot.egg-info/PKG-INFO
cz_sqlglot.egg-info/SOURCES.txt
cz_sqlglot.egg-info/dependency_links.txt
cz_sqlglot.egg-info/requires.txt
cz_sqlglot.egg-info/top_level.txt
sqlglot/__init__.py
sqlglot/__main__.py
sqlglot/_typing.py
sqlglot/_version.py
sqlglot/diff.py
sqlglot/errors.py
sqlglot/expressions.py
sqlglot/generator.py
sqlglot/helper.py
sqlglot/lineage.py
sqlglot/parser.py
sqlglot/planner.py
sqlglot/py.typed
sqlglot/schema.py
sqlglot/serde.py
sqlglot/time.py
sqlglot/tokens.py
sqlglot/transforms.py
sqlglot/trie.py
sqlglot/dataframe/__init__.py
sqlglot/dataframe/sql/__init__.py
sqlglot/dataframe/sql/_typing.py
sqlglot/dataframe/sql/column.py
sqlglot/dataframe/sql/dataframe.py
sqlglot/dataframe/sql/functions.py
sqlglot/dataframe/sql/group.py
sqlglot/dataframe/sql/normalize.py
sqlglot/dataframe/sql/operations.py
sqlglot/dataframe/sql/readwriter.py
sqlglot/dataframe/sql/session.py
sqlglot/dataframe/sql/transforms.py
sqlglot/dataframe/sql/types.py
sqlglot/dataframe/sql/util.py
sqlglot/dataframe/sql/window.py
sqlglot/dialects/__init__.py
sqlglot/dialects/bigquery.py
sqlglot/dialects/clickhouse.py
sqlglot/dialects/clickzetta.py
sqlglot/dialects/databricks.py
sqlglot/dialects/dialect.py
sqlglot/dialects/doris.py
sqlglot/dialects/drill.py
sqlglot/dialects/duckdb.py
sqlglot/dialects/hive.py
sqlglot/dialects/mysql.py
sqlglot/dialects/oracle.py
sqlglot/dialects/postgres.py
sqlglot/dialects/presto.py
sqlglot/dialects/redshift.py
sqlglot/dialects/snowflake.py
sqlglot/dialects/spark.py
sqlglot/dialects/spark2.py
sqlglot/dialects/sqlite.py
sqlglot/dialects/starrocks.py
sqlglot/dialects/tableau.py
sqlglot/dialects/teradata.py
sqlglot/dialects/trino.py
sqlglot/dialects/tsql.py
sqlglot/executor/__init__.py
sqlglot/executor/context.py
sqlglot/executor/env.py
sqlglot/executor/python.py
sqlglot/executor/table.py
sqlglot/optimizer/__init__.py
sqlglot/optimizer/annotate_types.py
sqlglot/optimizer/canonicalize.py
sqlglot/optimizer/eliminate_ctes.py
sqlglot/optimizer/eliminate_joins.py
sqlglot/optimizer/eliminate_subqueries.py
sqlglot/optimizer/isolate_table_selects.py
sqlglot/optimizer/merge_subqueries.py
