Metadata-Version: 2.1
Name: cz-sqlglot
Version: 0.0.1
Summary: An easily customizable SQL parser and transpiler
Home-page: https://github.com/tobymao/sqlglot
Author: Toby Mao
Author-email: toby.mao@gmail.com
License: MIT
Classifier: Development Status :: 5 - Production/Stable
Classifier: Intended Audience :: Developers
Classifier: Intended Audience :: Science/Research
Classifier: License :: OSI Approved :: MIT License
Classifier: Operating System :: OS Independent
Classifier: Programming Language :: SQL
Classifier: Programming Language :: Python :: 3 :: Only
Requires-Python: >=3.7
Provides-Extra: dev
License-File: LICENSE
